patternpiece/__init__.py
patternpiece/ac_matcher_nogil.c
patternpiece/ac_matcher_nogil.cpython-310-x86_64-linux-gnu.so
patternpiece/matcher.py
patternpiece/py.typed
patternpiece/version.py
patternpiece-1.0.1.dist-info/LICENSE
patternpiece-1.0.1.dist-info/METADATA
patternpiece-1.0.1.dist-info/WHEEL
patternpiece-1.0.1.dist-info/top_level.txt
patternpiece-1.0.1.dist-info/RECORD
