Metadata-Version: 2.1
Name: patternpiece
Version: 1.0.1
Author-email: Lvxiaowei Xu <xlxw@zju.edu.cn>, Zhiling Gong <zhilingong@zju.edu.cn>, Tianxiang Wang <wang_tx@zju.edu.cn>
License: Apache License
Project-URL: Homepage, https://github.com/xlxw/PatternPiece
Project-URL: Repository, https://github.com/xlxw/PatternPiece
Project-URL: Changelog, https://github.com/xlxw/PatternPiece/blob/main/CHANGELOG.md
Classifier: Intended Audience :: Science/Research
Classifier: Development Status :: 3 - Alpha
Classifier: License :: OSI Approved :: Apache Software License
Classifier: Programming Language :: Python :: 3
Classifier: Topic :: Scientific/Engineering :: Artificial Intelligence
Requires-Python: >=3.8
License-File: LICENSE
Requires-Dist: numpy
Provides-Extra: dev
Requires-Dist: ruff ; extra == 'dev'
Requires-Dist: mypy (<1.5,>=1.0) ; extra == 'dev'
Requires-Dist: black (<24.0,>=23.0) ; extra == 'dev'
Requires-Dist: isort (<5.13,>=5.12) ; extra == 'dev'
Requires-Dist: pytest ; extra == 'dev'
Requires-Dist: pytest-sphinx ; extra == 'dev'
Requires-Dist: pytest-cov ; extra == 'dev'
Requires-Dist: twine (>=1.11.0) ; extra == 'dev'
Requires-Dist: build ; extra == 'dev'
Requires-Dist: setuptools ; extra == 'dev'
Requires-Dist: wheel ; extra == 'dev'
Requires-Dist: Sphinx (<7.3.0,>=4.3.0) ; extra == 'dev'
Requires-Dist: furo (==2023.7.26) ; extra == 'dev'
Requires-Dist: myst-parser (<2.1,>=1.0) ; extra == 'dev'
Requires-Dist: sphinx-copybutton (==0.5.2) ; extra == 'dev'
Requires-Dist: sphinx-autobuild (==2021.3.14) ; extra == 'dev'
Requires-Dist: sphinx-autodoc-typehints (==1.23.3) ; extra == 'dev'
Requires-Dist: packaging ; extra == 'dev'
